monkeytale/__init__.py
monkeytale/file_management.py
monkeytale-0.3.3.dist-info/entry_points.txt
monkeytale-0.3.3.dist-info/WHEEL
monkeytale-0.3.3.dist-info/METADATA
monkeytale-0.3.3.dist-info/license_files/LICENSE
monkeytale-0.3.3.dist-info/RECORD
