Metadata-Version: 2.1
Name: monkeytale
Version: 0.3.3
Summary: An opinionated markup language for composing, documenting, and visualizing a novel outline.
License: Unlicense
Keywords: novel,structure,composition,documentation,visualization
Author-email: Monkeytale <monkeytale@dwlib.com>
Requires-Python: >=3.10
Classifier: Development Status :: 1 - Planning
Classifier: Intended Audience :: End Users/Desktop
Classifier: License :: OSI Approved :: The Unlicense (Unlicense)
Classifier: Programming Language :: Python :: 3.10
Classifier: Topic :: Documentation
Classifier: Topic :: Text Processing
Classifier: Topic :: Text Processing :: Linguistic
Classifier: Topic :: Text Processing :: Markup
Requires-Dist: click>=8.0.0
Requires-Dist: eliot>=1.14.0
Project-URL: Changelog, https://github.com/MLAOPDX/monkeytale/blob/main/CHANGELOG.md
Project-URL: Homepage, https://github.com/MLAOPDX/monkeytale/
Project-URL: Repository, https://github.com/MLAOPDX/monkeytale/
